{"Billid": "1183804", "BilllastUpdated": "2020-02-25T19:43:10", "Bill": "None", "BillIntroducedDate": "2004-02-10T10:15:00", "ParliamentSessionparliamentNumber": "37", "ParliamentSessionsessionNumber": "3", "ParliamentSession": "None", "BillNumberprefix": "C", "BillNumbernumber": "3", "BillNumber": "None", "BillTitle": "An Act to amend the Canada Elections Act and the Income Tax Act", "Titlelanguage": "fr", "ShortTitle": "None", "BillType": "House Government Bill", "SponsorAffiliationid": "51846", "SponsorAffiliation": "Leader of the Government in the House of Commons", "Personid": "306", "PersonGender": "M", "Person": "None", "FullName": "Paul Martin", "FirstName": "Paul", "MiddleName": "None", "LastName": "Martin", "PoliticalParty": "Liberal", "abbreviation": "Lib.", "PrimeMinisterid": "51818", "PrimeMinister": "Prime Minister", "Statute": "None", "Year": "2004", "Chapter": "24", "Publications": "None", "Publicationid": "2331595", "Publication": "Royal Assent", "PublicationFiles": "None", "PublicationFilelanguage": "fr", "PublicationFilerelativePath": "//parl.ca/DocumentViewer/en/2331595?Language=F", "PublicationFile": "None", "EventslaagCurrentStage": "RoyalAssentGiven", "Events": "None", "LastMajorStageEvent": "None", "Eventid": "3256164", "Eventchamber": "SEN", "Eventdate": "2004-05-14", "EventmeetingNumber": "42", "Event": "None", "Committee": "None", "CommitteeMeetings": "None", "Status": "Royal Assent", "Description": "None", "Progress": "CRA", "LegislativeEvents": "None", "Committeeid": "16102", "CommitteesenateCommitteeId": "1011", "Committeeaccronym": "LCJC", "CommitteeMeetingnumber": "18", "CommitteeMeetingmeetingDateTime": "2004-05-06T10:55:00", "CommitteeMeetingmeetingDate": "2004-05-06", "CommitteeMeetingmeetingTime": "10:55", "CommitteeMeetingstudyActivityId": "0", "CommitteeMeeting": "None"}