{"Billid": "3629244", "BilllastUpdated": "2020-02-25T16:23:17", "Bill": "None", "BillIntroducedDate": "2009-01-28T15:12:43", "ParliamentSessionparliamentNumber": "40", "ParliamentSessionsessionNumber": "2", "ParliamentSession": "None", "BillNumberprefix": "C", "BillNumbernumber": "5", "BillNumber": "None", "BillTitle": "An Act to amend the Indian Oil and Gas Act", "Titlelanguage": "fr", "ShortTitle": "None", "BillType": "House Government Bill", "SponsorAffiliationid": "111563", "SponsorAffiliation": "Minister of Indian Affairs and Northern Development and Federal Interlocutor for M\u00e9tis and Non-Status Indians", "Personid": "1733", "PersonGender": "M", "Person": "None", "FullName": "Stephen Harper", "FirstName": "Stephen", "MiddleName": "None", "LastName": "Harper", "PoliticalParty": "Conservative", "abbreviation": "CPC", "PrimeMinisterid": "78738", "PrimeMinister": "Prime Minister", "Statute": "None", "Year": "2009", "Chapter": "7", "Publications": "None", "Publicationid": "3908247", "Publication": "Royal Assent", "PublicationFiles": "None", "PublicationFilelanguage": "fr", "PublicationFilerelativePath": "//parl.ca/DocumentViewer/en/3908247?Language=F", "PublicationFile": "None", "EventslaagCurrentStage": "RoyalAssentGiven", "Events": "None", "LastMajorStageEvent": "None", "Eventid": "3262190", "Eventchamber": "SEN", "Eventdate": "2009-05-14", "EventmeetingNumber": "36", "Event": "None", "Committee": "None", "CommitteeMeetings": "None", "Status": "Royal Assent", "Description": "None", "Progress": "CRA", "LegislativeEvents": "None", "Committeeid": "16093", "CommitteesenateCommitteeId": "1001", "Committeeaccronym": "APPA", "CommitteeMeetingnumber": "11", "CommitteeMeetingmeetingDateTime": "2009-05-05T09:30:00", "CommitteeMeetingmeetingDate": "2009-05-05", "CommitteeMeetingmeetingTime": "09:30", "CommitteeMeetingstudyActivityId": "0", "CommitteeMeeting": "None"}