{"Billid": "4336828", "BilllastUpdated": "2020-02-25T17:15:02", "Bill": "None", "BillIntroducedDate": "2010-03-11T10:03:30", "ParliamentSessionparliamentNumber": "40", "ParliamentSessionsessionNumber": "3", "ParliamentSession": "None", "BillNumberprefix": "C", "BillNumbernumber": "3", "BillNumber": "None", "BillTitle": "An Act to promote gender equity in Indian registration by responding to the Court of Appeal for British Columbia decision in McIvor v. Canada (Registrar of Indian and Northern Affairs)", "Titlelanguage": "fr", "ShortTitle": "Gender Equity in Indian Registration Act", "BillType": "House Government Bill", "SponsorAffiliationid": "157731", "SponsorAffiliation": "Minister of Indian Affairs and Northern Development, Federal Interlocutor for M\u00e9tis and Non-Status Indians and Minister of the Canadian Northern Economic Development Agency", "Personid": "1733", "PersonGender": "M", "Person": "None", "FullName": "Stephen Harper", "FirstName": "Stephen", "MiddleName": "None", "LastName": "Harper", "PoliticalParty": "Conservative", "abbreviation": "CPC", "PrimeMinisterid": "78738", "PrimeMinister": "Prime Minister", "Statute": "None", "Year": "2010", "Chapter": "18", "Publications": "None", "Publicationid": "4901865", "Publication": "Royal Assent", "PublicationFiles": "None", "PublicationFilelanguage": "fr", "PublicationFilerelativePath": "//parl.ca/DocumentViewer/en/4901865?Language=F", "PublicationFile": "None", "EventslaagCurrentStage": "RoyalAssentGiven", "Events": "None", "LastMajorStageEvent": "None", "Eventid": "3690357", "Eventchamber": "SEN", "Eventdate": "2010-12-15", "EventmeetingNumber": "79", "Event": "None", "Committee": "None", "CommitteeMeetings": "None", "Status": "Royal Assent", "Description": "None", "Progress": "CRA", "LegislativeEvents": "None", "Committeeid": "16088", "CommitteesenateCommitteeId": "1077", "Committeeaccronym": "RIDR", "CommitteeMeetingnumber": "18", "CommitteeMeetingmeetingDateTime": "2010-12-06T15:02:00", "CommitteeMeetingmeetingDate": "2010-12-06", "CommitteeMeetingmeetingTime": "15:02", "CommitteeMeetingstudyActivityId": "0", "CommitteeMeeting": "None"}