{"Billid": "5254650", "BilllastUpdated": "2020-02-25T19:35:05", "Bill": "None", "BillIntroducedDate": "2011-11-22T10:05:06", "ParliamentSessionparliamentNumber": "41", "ParliamentSessionsessionNumber": "1", "ParliamentSession": "None", "BillNumberprefix": "C", "BillNumbernumber": "26", "BillNumber": "None", "BillTitle": "An Act to amend the Criminal Code (citizen's arrest and the defences of property and persons)", "Titlelanguage": "fr", "ShortTitle": "Citizen's Arrest and Self-defence Act", "BillType": "House Government Bill", "SponsorAffiliationid": "105824", "SponsorAffiliation": "Minister of Justice", "Personid": "1733", "PersonGender": "M", "Person": "None", "FullName": "Stephen Harper", "FirstName": "Stephen", "MiddleName": "None", "LastName": "Harper", "PoliticalParty": "Conservative", "abbreviation": "CPC", "PrimeMinisterid": "78738", "PrimeMinister": "Prime Minister", "Statute": "None", "Year": "2012", "Chapter": "9", "Publications": "None", "Publicationid": "5697359", "Publication": "Royal Assent", "PublicationFiles": "None", "PublicationFilelanguage": "fr", "PublicationFilerelativePath": "//parl.ca/DocumentViewer/en/5697359?Language=F", "PublicationFile": "None", "EventslaagCurrentStage": "RoyalAssentGiven", "Events": "None", "LastMajorStageEvent": "None", "Eventid": "7667784", "Eventchamber": "SEN", "Eventdate": "2012-06-28", "EventmeetingNumber": "99", "Event": "None", "Committee": "None", "CommitteeMeetings": "None", "Status": "Royal Assent", "Description": "None", "Progress": "CRA", "LegislativeEvents": "None", "Committeeid": "16102", "CommitteesenateCommitteeId": "1011", "Committeeaccronym": "LCJC", "CommitteeMeetingnumber": "48", "CommitteeMeetingmeetingDateTime": "2012-06-07T10:31:00", "CommitteeMeetingmeetingDate": "2012-06-07", "CommitteeMeetingmeetingTime": "10:31", "CommitteeMeetingstudyActivityId": "0", "CommitteeMeeting": "None"}